{"swagger":"2.0","host":"88.208.212.245","basePath":"/api/index.php","produces":["application/json","application/xml"],"consumes":["application/json","application/xml","multipart/form-data"],"paths":{"/donations/{id}":{"get":{"operationId":"retrieveDonations","tags":["donations"],"parameters":[{"name":"id","type":"integer","format":"int64","description":"ID of order","in":"path","required":true}],"summary":"Get properties of an donation object ??","description":"Return an array with donation informations","responses":{"200":{"description":"Success","schema":{"type":"string"}},"500":{"description":"RestException"}},"security":[{"api_key":[]}]},"put":{"operationId":"updateDonations","tags":["donations"],"parameters":[{"name":"id","type":"integer","format":"int64","description":"Id of order to update","in":"path","required":true},{"name":"updateDonationsModel","description":"request_data  \n","in":"body","required":false,"schema":{"$ref":"#/definitions/updateDonationsModel"}}],"summary":"Update order general fields (won't touch lines of order) ??","description":"","responses":{"200":{"description":"Success","schema":{"type":"integer","format":"int64"}}},"security":[{"api_key":[]}]},"delete":{"operationId":"removeDonations","tags":["donations"],"parameters":[{"name":"id","type":"integer","format":"int64","description":"Order ID","in":"path","required":true}],"summary":"Delete donation ??","description":"","responses":{"200":{"description":"Success","schema":{"type":"array","items":{"type":"string"}}}},"security":[{"api_key":[]}]},"from":["swagger_financial.json"]},"/donations":{"get":{"operationId":"listDonations","tags":["donations"],"parameters":[{"name":"sortfield","type":"string","defaultValue":"t.rowid","description":"Sort field","in":"query","required":false},{"name":"sortorder","type":"string","defaultValue":"ASC","description":"Sort order","in":"query","required":false},{"name":"limit","type":"integer","format":"int64","defaultValue":100,"description":"Limit for list","in":"query","required":false},{"name":"page","type":"integer","format":"int64","description":"Page number","in":"query","required":false},{"name":"thirdparty_ids","type":"string","description":"Thirdparty ids to filter orders of (example '1' or '1,2,3')","in":"query","required":false},{"name":"sqlfilters","type":"string","description":"Other criteria to filter answers separated by a comma. Syntax example \"(t.ref:like:'SO-%') and (t.date_creation:<:'20160101')\"","in":"query","required":false}],"summary":"List donations ??","description":"Get a list of donations","responses":{"200":{"description":"Success","schema":{"type":"array","items":{"type":"string"}}},"500":{"description":"RestException"}},"security":[{"api_key":[]}]},"post":{"operationId":"createDonations","tags":["donations"],"parameters":[{"name":"createDonationsModel","description":"request_data  \n","in":"body","required":false,"schema":{"$ref":"#/definitions/createDonationsModel"}}],"summary":"Create donation object ??","description":"","responses":{"200":{"description":"Success","schema":{"type":"integer","format":"int64"}}},"security":[{"api_key":[]}]},"from":["swagger_financial.json"]},"/donations/{id}/validate":{"post":{"operationId":"donationsValidate","tags":["donations"],"parameters":[{"name":"id","type":"integer","format":"int64","description":"Order ID","in":"path","required":true},{"name":"donationsValidateModel","description":"idwarehouse  \nnotrigger  \n","in":"body","required":false,"schema":{"$ref":"#/definitions/donationsValidateModel"}}],"summary":"Validate an donation ??","description":"If you get a bad value for param notrigger check, provide this in body { \"idwarehouse\": 0, \"notrigger\": 0 }","responses":{"200":{"description":"Success","schema":{"type":"array","items":{"type":"string"}}},"304":{"description":"Not Modified"},"401":{"description":"Unauthorized"},"404":{"description":"Not Found"},"500":{"description":"System error"}},"security":[{"api_key":[]}]},"from":["swagger_financial.json"]}},"definitions":{"updateDonationsModel":{"properties":{"request_data":{"type":"array","items":{"type":"string"},"description":"Datas"}},"from":["swagger_financial.json"]},"createDonationsModel":{"properties":{"request_data":{"type":"array","items":{"type":"string"},"description":"Request data"}},"from":["swagger_financial.json"]},"donationsValidateModel":{"properties":{"idwarehouse":{"type":"integer","format":"int64","description":"Warehouse ID"},"notrigger":{"type":"integer","format":"int64","description":"1=Does not execute triggers, 0= execute triggers"}},"from":["swagger_financial.json"]}},"securityDefinitions":{"api_key":{"type":"apiKey","name":"api_key","in":"query"}},"info":{"version":"1","title":"Restler API Explorer","description":"Live API Documentation","contact":{"name":"Restler Support","url":"luracast.com/products/restler","email":"arul@luracast.com"},"license":{"name":"LGPL-2.1","url":"https://www.gnu.org/licenses/old-licenses/lgpl-2.1.html"}}}